yaml_replace/__init__.py
yaml_replace/_utils.py
yaml_replace/_yaml_template.py
yaml_replace-1.1.2.dist-info/LICENSE
yaml_replace-1.1.2.dist-info/METADATA
yaml_replace-1.1.2.dist-info/WHEEL
yaml_replace-1.1.2.dist-info/RECORD
